structural_diversity_index/MeetingTimeEstimator.py
structural_diversity_index/MeetingTimeUI.py
structural_diversity_index/RandomWalkSimulator.py
structural_diversity_index/RandomWalkSimulatorCUDA.py
structural_diversity_index/__init__.py
structural_diversity_index-0.0.7.dist-info/LICENSE
structural_diversity_index-0.0.7.dist-info/METADATA
structural_diversity_index-0.0.7.dist-info/WHEEL
structural_diversity_index-0.0.7.dist-info/top_level.txt
structural_diversity_index-0.0.7.dist-info/RECORD
