Metadata-Version: 2.1
Name: structural-diversity-index
Version: 0.0.7
Summary: A package for fast numerical computation of the structural diversity index of arbitrary networks
Author-email: Andrea Musso <andreamusso96@gmail.com>
License: MIT License        
Project-URL: Homepage, https://github.com/ethz-coss/RSE-Distance
Project-URL: Documentation, https://rse-distance.readthedocs.io/en/latest/
Classifier: Programming Language :: Python :: 3
Classifier: License :: OSI Approved :: MIT License
Classifier: Operating System :: OS Independent
Requires-Python: >=3.7
License-File: LICENSE
Requires-Dist: scipy (>=1.7.3)
Requires-Dist: numpy (>=1.22.1)
Requires-Dist: torch (>=1.10)
Requires-Dist: tqdm (>=4.62.3)
Requires-Dist: networkx (>=2.8)
Provides-Extra: cuda
Requires-Dist: cupy-cuda11x (>=9.4.0) ; extra == 'cuda'
